caffe/__init__.py
caffe/_caffe.so
caffe/classifier.py
caffe/coord_map.py
caffe/detector.py
caffe/draw.py
caffe/io.py
caffe/model_libs.py
caffe/net_spec.py
caffe/pycaffe.py
caffe/proto/__init__.py
caffe/proto/caffe_pb2.py
caffe_ssd-0.1.dist-info/METADATA
caffe_ssd-0.1.dist-info/WHEEL
caffe_ssd-0.1.dist-info/top_level.txt
caffe_ssd-0.1.dist-info/RECORD
