Metadata-Version: 2.1
Name: caffe-ssd
Version: 0.1
Summary: weiliu89 caffe-ssd
Home-page: UNKNOWN
Author: UNKNOWN
Author-email: UNKNOWN
License: UNKNOWN
Platform: UNKNOWN
